garf/community/google/ads/__init__.py
garf/community/google/ads/api_clients.py
garf/community/google/ads/exceptions.py
garf/community/google/ads/parsers.py
garf/community/google/ads/query_editor.py
garf/community/google/ads/report_fetcher.py
garf/community/google/ads/search_ads_360_client.py
garf/community/google/ads/simulator.py
garf/community/google/ads/builtins/__init__.py
garf/community/google/ads/builtins/ocid_mapping.py
garf_google_ads/__init__.py
garf_google_ads/api_clients.py
garf_google_ads/exceptions.py
garf_google_ads/parsers.py
garf_google_ads/query_editor.py
garf_google_ads/report_fetcher.py
garf_google_ads/simulator.py
garf_google_ads/builtins/__init__.py
garf_google_ads/builtins/ocid_mapping.py
garf_google_ads-1.1.1.dist-info/METADATA
garf_google_ads-1.1.1.dist-info/WHEEL
garf_google_ads-1.1.1.dist-info/entry_points.txt
garf_google_ads-1.1.1.dist-info/top_level.txt
garf_google_ads-1.1.1.dist-info/RECORD
