Metadata-Version: 2.4
Name: garf-google-ads
Version: 1.1.1
Summary: Garf implementation for Google Ads API
Author-email: Andrei Markin <amarkin@google.com>, "Google Inc. (gTech gPS CSE team)" <no-reply@google.com>
License: Apache 2.0
Classifier: Development Status :: 4 - Beta
Classifier: Programming Language :: Python
Requires-Python: >=3.9
Requires-Dist: garf-core>=1.0.0
Requires-Dist: garf-io>=1.0.0
Requires-Dist: google-ads
Requires-Dist: tenacity
Provides-Extra: test
Requires-Dist: pytest; extra == "test"
Requires-Dist: pytest-cov; extra == "test"
Requires-Dist: python-dotenv; extra == "test"
Provides-Extra: search-ads-360
Requires-Dist: google-api-python-client; extra == "search-ads-360"
